baybe/__init__.py
baybe/campaign.py
baybe/exceptions.py
baybe/py.typed
baybe/_optional/__init__.py
baybe/_optional/chem.py
baybe/_optional/fpsample.py
baybe/_optional/info.py
baybe/_optional/insights.py
baybe/_optional/ngboost.py
baybe/_optional/onnx.py
baybe/_optional/polars.py
baybe/_optional/simulation.py
baybe/acquisition/__init__.py
baybe/acquisition/_builder.py
baybe/acquisition/acqfs.py
baybe/acquisition/base.py
baybe/acquisition/partial.py
baybe/acquisition/utils.py
baybe/constraints/__init__.py
baybe/constraints/base.py
baybe/constraints/conditions.py
baybe/constraints/continuous.py
baybe/constraints/deprecation.py
baybe/constraints/discrete.py
baybe/constraints/utils.py
baybe/constraints/validation.py
baybe/insights/__init__.py
baybe/insights/shap.py
baybe/kernels/__init__.py
baybe/kernels/base.py
baybe/kernels/basic.py
baybe/kernels/composite.py
baybe/objectives/__init__.py
baybe/objectives/base.py
baybe/objectives/botorch.py
baybe/objectives/desirability.py
baybe/objectives/enum.py
baybe/objectives/pareto.py
baybe/objectives/single.py
baybe/objectives/validation.py
baybe/parameters/__init__.py
baybe/parameters/base.py
baybe/parameters/categorical.py
baybe/parameters/custom.py
baybe/parameters/enum.py
baybe/parameters/numerical.py
baybe/parameters/substance.py
baybe/parameters/utils.py
baybe/parameters/validation.py
baybe/priors/__init__.py
baybe/priors/base.py
baybe/priors/basic.py
baybe/recommenders/__init__.py
baybe/recommenders/base.py
baybe/recommenders/naive.py
baybe/recommenders/meta/__init__.py
baybe/recommenders/meta/base.py
baybe/recommenders/meta/sequential.py
baybe/recommenders/pure/__init__.py
baybe/recommenders/pure/base.py
baybe/recommenders/pure/bayesian/__init__.py
baybe/recommenders/pure/bayesian/base.py
baybe/recommenders/pure/bayesian/botorch.py
baybe/recommenders/pure/nonpredictive/__init__.py
baybe/recommenders/pure/nonpredictive/base.py
baybe/recommenders/pure/nonpredictive/clustering.py
baybe-0.14.2.dist-info/licenses/LICENSE
baybe-0.14.2.dist-info/METADATA
baybe-0.14.2.dist-info/WHEEL
baybe-0.14.2.dist-info/top_level.txt
baybe-0.14.2.dist-info/RECORD
