Metadata-Version: 2.4
Name: baybe
Version: 0.14.2
Summary: A Bayesian Back End for Design of Experiments
Author: Merck KGaA, Darmstadt, Germany
License: Apache-2.0
Project-URL: Homepage, https://emdgroup.github.io/baybe/
Project-URL: Documentation, https://emdgroup.github.io/baybe/_autosummary/baybe.html
Project-URL: Changelog, https://emdgroup.github.io/baybe/misc/changelog_link.html
Project-URL: GitHub, https://github.com/emdgroup/baybe/
Project-URL: Issues, https://github.com/emdgroup/baybe/issues/
Keywords: Active Learning,Bayesian Optimization,Design of Experiments,DOE,Optimization
Classifier: Development Status :: 4 - Beta
Classifier: Intended Audience :: Developers
Classifier: License :: OSI Approved :: Apache Software License
Classifier: Programming Language :: Python
Classifier: Programming Language :: Python :: 3 :: Only
Classifier: Programming Language :: Python :: 3.10
Classifier: Programming Language :: Python :: 3.11
Classifier: Programming Language :: Python :: 3.12
Classifier: Programming Language :: Python :: 3.13
Classifier: Operating System :: OS Independent
Classifier: Typing :: Typed
Requires-Python: <3.14,>=3.10
License-File: LICENSE
Requires-Dist: attrs>=25.4.0
Requires-Dist: botorch<1,>=0.13.0
Requires-Dist: cattrs>=25.2.0
Requires-Dist: exceptiongroup
Requires-Dist: gpytorch<2,>=1.9.1
Requires-Dist: joblib<2,>1.4.0
Requires-Dist: numpy<3,>=1.24.1
Requires-Dist: pandas<3,>=1.4.2
Requires-Dist: scikit-learn<2,>=1.1.1
Requires-Dist: scipy>=1.10.1
Requires-Dist: torch<3,>=1.13.1
Requires-Dist: typing_extensions>=4.7.0
Provides-Extra: extras
Requires-Dist: baybe[chem]; extra == "extras"
Requires-Dist: baybe[insights]; extra == "extras"
Requires-Dist: baybe[onnx]; extra == "extras"
Requires-Dist: baybe[polars]; extra == "extras"
Requires-Dist: baybe[simulation]; extra == "extras"
Requires-Dist: ngboost<1,>=0.3.12; extra == "extras"
Requires-Dist: fpsample>=1.0.1; extra == "extras"
Provides-Extra: chem
Requires-Dist: scikit-fingerprints>=1.13.1; extra == "chem"
Provides-Extra: onnx
Requires-Dist: onnx>=1.16.0; extra == "onnx"
Requires-Dist: onnxruntime>=1.15.1; extra == "onnx"
Requires-Dist: skl2onnx>=1.19.1; extra == "onnx"
Provides-Extra: dev
Requires-Dist: baybe[examples]; extra == "dev"
Requires-Dist: baybe[docs]; extra == "dev"
Requires-Dist: baybe[lint]; extra == "dev"
Requires-Dist: baybe[mypy]; extra == "dev"
Requires-Dist: baybe[test]; extra == "dev"
Requires-Dist: baybe[benchmarking]; extra == "dev"
Requires-Dist: pip-audit>=2.5.5; extra == "dev"
Requires-Dist: setuptools-scm>=7.1.0; extra == "dev"
Requires-Dist: tox-uv>=1.7.0; extra == "dev"
Requires-Dist: uv>=0.9.25; extra == "dev"
Provides-Extra: insights
Requires-Dist: shap[others]>=0.46.0; extra == "insights"
Provides-Extra: docs
Requires-Dist: baybe[examples]; extra == "docs"
Requires-Dist: furo>=2023.09.10; extra == "docs"
Requires-Dist: jupyter>=1.1.1; extra == "docs"
Requires-Dist: jupytext>=1.16.4; extra == "docs"
Requires-Dist: myst-parser>=4.0.0; extra == "docs"
Requires-Dist: sphinx>=8.0.2; extra == "docs"
Requires-Dist: sphinx-autodoc-typehints>=2.4.4; extra == "docs"
Requires-Dist: sphinx-copybutton==0.5.2; extra == "docs"
Requires-Dist: sphinx-paramlinks==0.6.0; extra == "docs"
Requires-Dist: sphinx-design==0.6.1; extra == "docs"
Requires-Dist: sphinxcontrib-bibtex>=2.6.2; extra == "docs"
Requires-Dist: tqdm; extra == "docs"
Provides-Extra: examples
Requires-Dist: baybe[extras]; extra == "examples"
Requires-Dist: matplotlib!=3.9.1,>=3.7.3; extra == "examples"
Requires-Dist: openpyxl>=3.0.9; extra == "examples"
Requires-Dist: pillow>=10.0.1; extra == "examples"
Requires-Dist: plotly>=5.10.0; extra == "examples"
Requires-Dist: seaborn>=0.12.2; extra == "examples"
Requires-Dist: streamlit>=1.37.0; extra == "examples"
Requires-Dist: tornado>=6.3.3; extra == "examples"
Provides-Extra: lint
Requires-Dist: flake8==7.3.0; extra == "lint"
Requires-Dist: pre-commit==4.2.0; extra == "lint"
Requires-Dist: pydoclint==0.5.5; extra == "lint"
Requires-Dist: pyupgrade==3.21.2; extra == "lint"
Requires-Dist: ruff==0.14.11; extra == "lint"
Provides-Extra: mypy
Requires-Dist: mypy>=1.10.1; extra == "mypy"
Requires-Dist: pandas-stubs>=2.2.2.240603; extra == "mypy"
Requires-Dist: types-seaborn>=0.13.2.20240618; extra == "mypy"
Requires-Dist: types-psutil>=7.0.0.20250801; extra == "mypy"
Requires-Dist: types-tqdm; extra == "mypy"
Provides-Extra: polars
Requires-Dist: polars[pyarrow]<2,>=0.19.19; extra == "polars"
Provides-Extra: simulation
Requires-Dist: xyzpy>=1.2.1; extra == "simulation"
Provides-Extra: benchmarking
Requires-Dist: baybe[chem]; extra == "benchmarking"
Requires-Dist: baybe[onnx]; extra == "benchmarking"
Requires-Dist: baybe[simulation]; extra == "benchmarking"
Requires-Dist: baybe[examples]; extra == "benchmarking"
Requires-Dist: boto3<2,>=1.0.0; extra == "benchmarking"
Requires-Dist: GitPython<4,>=3.0.6; extra == "benchmarking"
Requires-Dist: psutil>=7.0.0; extra == "benchmarking"
Requires-Dist: torch>=2.4.0; extra == "benchmarking"
Provides-Extra: test
Requires-Dist: hypothesis[pandas]>=6.88.4; extra == "test"
Requires-Dist: tenacity>=8.5.0; extra == "test"
Requires-Dist: pytest>=7.2.0; extra == "test"
Requires-Dist: pytest-cov>=4.1.0; extra == "test"
Dynamic: license-file
